pymongowatch_attributes.py
pymongo/watcher/__init__.py
pymongo/watcher/bases.py
pymongo/watcher/collection.py
pymongo/watcher/csv_utils.py
pymongo/watcher/cursor.py
pymongo/watcher/filters.py
pymongo/watcher/logger.py
pymongo/watcher/transforms.py
pymongo_mask/pymongo.py
pymongowatch-1.0.0.data/data/etc/pymongowatch.yaml
pymongowatch_mask_installer/__init__.py
pymongowatch_mask_installer/main.py
pymongowatch-1.0.0.dist-info/LICENSE.org
pymongowatch-1.0.0.dist-info/METADATA
pymongowatch-1.0.0.dist-info/WHEEL
pymongowatch-1.0.0.dist-info/entry_points.txt
pymongowatch-1.0.0.dist-info/top_level.txt
pymongowatch-1.0.0.dist-info/RECORD
