Metadata-Version: 2.1
Name: pymongowatch
Version: 1.0.0
Summary: A pymongo extension for auditing the database operations
Home-page: https://github.com/admirito/pymongowatch
Author: Mohammad Razavi
Author-email: mrazavi64@gmail.com
License: GPLv3+
Keywords: mongo,mongodb,pymongo,log,logging
Platform: UNKNOWN
Classifier: Development Status :: 3 - Alpha
Classifier: Intended Audience :: Developers
Classifier: Intended Audience :: System Administrators
Classifier: License :: OSI Approved :: GNU General Public License v3 or later (GPLv3+)
Classifier: Operating System :: OS Independent
Classifier: Natural Language :: English
Classifier: Programming Language :: Python :: 3
Classifier: Programming Language :: Python :: 3.8
Classifier: Topic :: System :: Logging
Classifier: Topic :: System :: Systems Administration
Requires-Dist: pymongo
Requires-Dist: pyyaml
